README.md
setup.py
open_weather_api/__init__.py
open_weather_api/api.py
open_weather_api/config.py
open_weather_api/constants.py
open_weather_api/options/__init__.py
open_weather_api/options/city.py
open_weather_api/options/coordinates.py
owm_api_mugan86.egg-info/PKG-INFO
owm_api_mugan86.egg-info/SOURCES.txt
owm_api_mugan86.egg-info/dependency_links.txt
owm_api_mugan86.egg-info/top_level.txt