Metadata-Version: 2.1
Name: owm-api-mugan86
Version: 0.0.2
Summary: Obtener la información del tiempo actual y previsión con Openweather Map Api
Home-page: https://github.com/mugan86/frontend-meang-online-shop
Author: Anartz Mugika Ledo
Author-email: mugan86@gmail.com
License: UNKNOWN
Project-URL: Bug Tracker, https://github.com/mugan86/frontend-meang-online-shop/issues
Platform: UNKNOWN
Classifier: Programming Language :: Python :: 3
Classifier: License :: OSI Approved :: MIT License
Classifier: Operating System :: OS Independent
Requires-Python: >=3.6
